setup.cfg
setup.py
bin/dirpy
dirpy/__init__.py
dirpy.egg-info/PKG-INFO
dirpy.egg-info/SOURCES.txt
dirpy.egg-info/dependency_links.txt
dirpy.egg-info/top_level.txt